extract-thai/__init__.py
extract-thai/main.py
extract_thai/__init__.py
extract_thai/extract_thai.py
thai-extractor/__init__.py
thai-extractor/main.py
extract_thai-0.0.1.dist-info/METADATA
extract_thai-0.0.1.dist-info/WHEEL
extract_thai-0.0.1.dist-info/entry_points.txt
extract_thai-0.0.1.dist-info/top_level.txt
extract_thai-0.0.1.dist-info/RECORD
