Metadata-Version: 2.1
Name: extract-thai
Version: 0.0.1
Summary: Thai Text Extractor from Images
Author: JayTrairat
Author-email: jay.trairat@gmail.com
Classifier: Development Status :: 5 - Production/Stable
Classifier: Intended Audience :: Developers
Classifier: License :: OSI Approved :: MIT License
Classifier: Programming Language :: Python :: 3
Classifier: Programming Language :: Python :: 3.6
Classifier: Programming Language :: Python :: 3.7
Classifier: Programming Language :: Python :: 3.8
Classifier: Programming Language :: Python :: 3.9
Requires-Dist: Pillow
Requires-Dist: pytesseract
